x_decorator/__init__.py
x_decorator/parallel_apply.py
x_decorator/retry.py
x_decorator/search.py
x_decorator/timer.py
xwyzsn_decorator-0.0.5.dist-info/METADATA
xwyzsn_decorator-0.0.5.dist-info/WHEEL
xwyzsn_decorator-0.0.5.dist-info/RECORD
